vaulty.py
vaulty-0.1.0.dist-info/DESCRIPTION.rst
vaulty-0.1.0.dist-info/METADATA
vaulty-0.1.0.dist-info/RECORD
vaulty-0.1.0.dist-info/WHEEL
vaulty-0.1.0.dist-info/entry_points.txt
vaulty-0.1.0.dist-info/metadata.json
vaulty-0.1.0.dist-info/top_level.txt
